rda_package/__init__.py
rda_package/rda.py
rda_package-0.0.4.dist-info/LICENSE.txt
rda_package-0.0.4.dist-info/METADATA
rda_package-0.0.4.dist-info/WHEEL
rda_package-0.0.4.dist-info/top_level.txt
rda_package-0.0.4.dist-info/RECORD
