Metadata-Version: 2.1
Name: rda-package
Version: 0.0.4
Summary: rhythmic data analysis package
Home-page: https://github.com/VESTUArthur/RDA
Author: VESTUArthur
Author-email: vestuarthur@gmail.com
Project-URL: Bug Tracker, https://github.com/VESTUArthur/RDA/issues
Classifier: Programming Language :: Python :: 3
Classifier: License :: OSI Approved :: MIT License
Classifier: Operating System :: OS Independent
Requires-Python: >=3.6
License-File: LICENSE.txt
Requires-Dist: numpy
Requires-Dist: pandas
Requires-Dist: sklearn
Requires-Dist: plotly
Requires-Dist: rpy2
Requires-Dist: CosinorPy
Requires-Dist: matplotlib
Requires-Dist: matplotlib-venn
Requires-Dist: seaborn
Requires-Dist: statsmodels
